lmdoctor/__init__.py
lmdoctor/control_utils.py
lmdoctor/detection_utils.py
lmdoctor/doctor.py
lmdoctor/extraction_utils.py
lmdoctor/plot_utils.py
lmdoctor/probe_utils.py
lmdoctor/utils.py
lmdoctor/data/emotions/anger.json
lmdoctor/data/emotions/disgust.json
lmdoctor/data/emotions/fear.json
lmdoctor/data/emotions/happiness.json
lmdoctor/data/emotions/sadness.json
lmdoctor/data/emotions/surprise.json
lmdoctor/data/ethics/commonsense/cm_train.csv
lmdoctor/data/facts/facts_true_false.csv
lmdoctor/data/fairness/dev.json
lmdoctor/data/harmlessness/instructions.csv
lmdoctor/target_specific_utils/__init__.py
lmdoctor/target_specific_utils/emotion_utils.py
lmdoctor/target_specific_utils/fairness_utils.py
lmdoctor/target_specific_utils/harmlessness_utils.py
lmdoctor/target_specific_utils/honesty_utils.py
lmdoctor/target_specific_utils/morality_utils.py
lmdoctor-0.5.7.dist-info/LICENSE
lmdoctor-0.5.7.dist-info/METADATA
lmdoctor-0.5.7.dist-info/WHEEL
lmdoctor-0.5.7.dist-info/top_level.txt
lmdoctor-0.5.7.dist-info/RECORD
