Metadata-Version: 2.2
Name: lmdoctor
Version: 0.5.7
Summary: Extract, detect, and control representations within language models as they read and write text.
Home-page: https://github.com/joshlevy89/lmdoctor
Author: Josh Levy
Author-email: joshlevy89@gmail.com
License: MIT
Classifier: Development Status :: 2 - Pre-Alpha
Classifier: Intended Audience :: Science/Research
Classifier: License :: OSI Approved :: MIT License
Classifier: Operating System :: POSIX :: Linux
Classifier: Programming Language :: Python :: 3.10
License-File: LICENSE
Requires-Dist: jupyter
Requires-Dist: ipykernel
Requires-Dist: transformers==4.36.2
Requires-Dist: plotly
Requires-Dist: tokenizers==0.15.2
Requires-Dist: peft==0.10.0
Requires-Dist: scikit-learn
Requires-Dist: pandas
Dynamic: author
Dynamic: author-email
Dynamic: classifier
Dynamic: description
Dynamic: description-content-type
Dynamic: home-page
Dynamic: license
Dynamic: requires-dist
Dynamic: summary
